converter_chinkara/converter.py
converter_chinkara-0.0.1.dist-info/METADATA
converter_chinkara-0.0.1.dist-info/WHEEL
converter_chinkara-0.0.1.dist-info/licenses/LICENSE
converter_chinkara-0.0.1.dist-info/RECORD
