Metadata-Version: 2.1
Name: converter_chinkara
Version: 0.0.1
Summary: A simple binary to decimal converter and decimal to binary
Project-URL: Homepage, https://github.com/Ch1nkara/M1-2022-git-workflow-dubaret
Project-URL: Bug Tracker, https://github.com/Ch1nkara/M1-2022-git-workflow-dubaret/issues
Author-email: chinkara <vincent.du-baret@isen.yncrea.fr>
License-File: LICENSE
Classifier: License :: OSI Approved :: MIT License
Classifier: Operating System :: OS Independent
Classifier: Programming Language :: Python :: 3
Requires-Python: >=3.7
